{
  "stats": {
    "suites": 1,
    "tests": 2,
    "passes": 2,
    "pending": 0,
    "failures": 0,
    "start": "2021-03-09T16:24:01.773Z",
    "end": "2021-03-09T16:24:08.400Z",
    "duration": 6007,
    "testsRegistered": 2,
    "passPercent": 100,
    "pendingPercent": 0,
    "other": 0,
    "hasOther": false,
    "skipped": 0,
    "hasSkipped": false
  },
  "results": [
    {
      "uuid": "864cc6b8-125a-4fae-9bf6-3030c2c95927",
      "title": "",
      "fullFile": "cypress\\integration\\taskGenerateTableDom.spec.js",
      "file": "cypress\\integration\\taskGenerateTableDom.spec.js",
      "beforeHooks": [],
      "afterHooks": [],
      "tests": [],
      "suites": [
        {
          "uuid": "54e197b9-9a37-4541-abc3-0af6f36b1d3f",
          "title": "Generate table app",
          "fullFile": "",
          "file": "",
          "beforeHooks": [],
          "afterHooks": [],
          "tests": [
            {
              "title": "should create a table based on people.json file",
              "fullTitle": "Generate table app should create a table based on people.json file",
              "timedOut": null,
              "duration": 5595,
              "state": "passed",
              "speed": "slow",
              "pass": true,
              "fail": false,
              "pending": false,
              "context": null,
              "code": "for (var i = 0; i < people.length; i++) {\n  cy.contains('tr', people[i].name).contains('td', people[i].born);\n  cy.contains('tr', people[i].name).contains('td', people[i].died);\n  cy.contains('tr', people[i].name).contains(('td', people[i].died) - ('td', people[i].born));\n  cy.contains('tr', people[i].name).contains('td', Math.ceil(people[i].died / 100));\n  cy.contains('tr', people[i].name).contains('td', people[i].sex === 'm' ? 'Male' : 'Female');\n}",
              "err": {},
              "uuid": "1a8b53cf-e51d-4cff-a432-680d1c7d6af4",
              "parentUUID": "54e197b9-9a37-4541-abc3-0af6f36b1d3f",
              "isHook": false,
              "skipped": false
            },
            {
              "title": "shouldn't contain fatherName, motherName and slug in table",
              "fullTitle": "Generate table app shouldn't contain fatherName, motherName and slug in table",
              "timedOut": null,
              "duration": 412,
              "state": "passed",
              "speed": "slow",
              "pass": true,
              "fail": false,
              "pending": false,
              "context": null,
              "code": "cy.get('tbody').contains('Petrus de Milliano').should('not.exist');\ncy.get('tbody').contains('Laurentia van Vlaenderen').should('not.exist');\ncy.get('tbody').contains('jan-van-brussel-1714').should('not.exist');",
              "err": {},
              "uuid": "ac5ae631-2dc2-4ce2-b8cd-a0f9e7320eaa",
              "parentUUID": "54e197b9-9a37-4541-abc3-0af6f36b1d3f",
              "isHook": false,
              "skipped": false
            }
          ],
          "suites": [],
          "passes": [
            "1a8b53cf-e51d-4cff-a432-680d1c7d6af4",
            "ac5ae631-2dc2-4ce2-b8cd-a0f9e7320eaa"
          ],
          "failures": [],
          "pending": [],
          "skipped": [],
          "duration": 6007,
          "root": false,
          "rootEmpty": false,
          "_timeout": 2000
        }
      ],
      "passes": [],
      "failures": [],
      "pending": [],
      "skipped": [],
      "duration": 0,
      "root": true,
      "rootEmpty": true,
      "_timeout": 2000
    }
  ],
  "meta": {
    "mocha": {
      "version": "7.0.1"
    },
    "mochawesome": {
      "options": {
        "quiet": false,
        "reportFilename": "mochawesome",
        "saveHtml": false,
        "saveJson": true,
        "consoleReporter": "spec",
        "useInlineDiffs": false,
        "code": true
      },
      "version": "6.2.1"
    },
    "marge": {
      "options": {
        "reportDir": "raw_reports",
        "overwrite": false,
        "html": false,
        "json": true
      },
      "version": "5.1.0"
    }
  }
}