{
  "stats": {
    "suites": 1,
    "tests": 2,
    "passes": 1,
    "pending": 0,
    "failures": 1,
    "start": "2022-08-24T16:20:21.084Z",
    "end": "2022-08-24T16:20:25.931Z",
    "duration": 4774,
    "testsRegistered": 2,
    "passPercent": 50,
    "pendingPercent": 0,
    "other": 0,
    "hasOther": false,
    "skipped": 0,
    "hasSkipped": false
  },
  "results": [
    {
      "uuid": "14582395-ea27-4dbc-9230-135fe939550b",
      "title": "",
      "fullFile": "cypress\\integration\\taskGenerateTableDom.spec.js",
      "file": "cypress\\integration\\taskGenerateTableDom.spec.js",
      "beforeHooks": [],
      "afterHooks": [],
      "tests": [],
      "suites": [
        {
          "uuid": "6a5b1bb0-f0b5-43b7-b7a1-a2e74f07e149",
          "title": "Generate table app",
          "fullFile": "",
          "file": "",
          "beforeHooks": [],
          "afterHooks": [],
          "tests": [
            {
              "title": "should create a table based on people.json file",
              "fullTitle": "Generate table app should create a table based on people.json file",
              "timedOut": null,
              "duration": 4661,
              "state": "failed",
              "speed": null,
              "pass": false,
              "fail": true,
              "pending": false,
              "context": null,
              "code": "for (var i = 0; i < people.length; i++) {\n  cy.contains('tr', people[i].name).contains('td', people[i].born);\n  cy.contains('tr', people[i].name).contains('td', people[i].died);\n  cy.contains('tr', people[i].name).contains(('td', people[i].died) - ('td', people[i].born));\n  cy.contains('tr', people[i].name).contains('td', Math.ceil(people[i].died / 100));\n  cy.contains('tr', people[i].name).contains('td', people[i].sex === 'm' ? 'Male' : 'Female');\n}",
              "err": {
                "message": "AssertionError: Timed out retrying: Expected to find content: '1832' within the element: <tr> and with the selector: 'td' but never did.",
                "estack": "AssertionError: Timed out retrying: Expected to find content: '1832' within the element: <tr> and with the selector: 'td' but never did.\n    at Context.eval (http://localhost:8080/__cypress/tests?p=cypress\\integration\\taskGenerateTableDom.spec.js:107:41)",
                "diff": null
              },
              "uuid": "6e1a4e29-dbbd-4b9e-8281-28a837da6df6",
              "parentUUID": "6a5b1bb0-f0b5-43b7-b7a1-a2e74f07e149",
              "isHook": false,
              "skipped": false
            },
            {
              "title": "shouldn't contain fatherName, motherName and slug in table",
              "fullTitle": "Generate table app shouldn't contain fatherName, motherName and slug in table",
              "timedOut": null,
              "duration": 113,
              "state": "passed",
              "speed": "slow",
              "pass": true,
              "fail": false,
              "pending": false,
              "context": null,
              "code": "cy.get('tbody').contains('Petrus de Milliano').should('not.exist');\ncy.get('tbody').contains('Laurentia van Vlaenderen').should('not.exist');\ncy.get('tbody').contains('jan-van-brussel-1714').should('not.exist');",
              "err": {},
              "uuid": "06312a94-9da7-4985-ab45-caf7187b8883",
              "parentUUID": "6a5b1bb0-f0b5-43b7-b7a1-a2e74f07e149",
              "isHook": false,
              "skipped": false
            }
          ],
          "suites": [],
          "passes": [
            "06312a94-9da7-4985-ab45-caf7187b8883"
          ],
          "failures": [
            "6e1a4e29-dbbd-4b9e-8281-28a837da6df6"
          ],
          "pending": [],
          "skipped": [],
          "duration": 4774,
          "root": false,
          "rootEmpty": false,
          "_timeout": 2000
        }
      ],
      "passes": [],
      "failures": [],
      "pending": [],
      "skipped": [],
      "duration": 0,
      "root": true,
      "rootEmpty": true,
      "_timeout": 2000
    }
  ],
  "meta": {
    "mocha": {
      "version": "7.0.1"
    },
    "mochawesome": {
      "options": {
        "quiet": false,
        "reportFilename": "mochawesome",
        "saveHtml": false,
        "saveJson": true,
        "consoleReporter": "spec",
        "useInlineDiffs": false,
        "code": true
      },
      "version": "6.2.1"
    },
    "marge": {
      "options": {
        "reportDir": "raw_reports",
        "overwrite": false,
        "html": false,
        "json": true
      },
      "version": "5.1.0"
    }
  }
}