{
  "stats": {
    "suites": 1,
    "tests": 2,
    "passes": 2,
    "pending": 0,
    "failures": 0,
    "start": "2023-03-01T11:16:03.924Z",
    "end": "2023-03-01T11:16:04.949Z",
    "duration": 965,
    "testsRegistered": 2,
    "passPercent": 100,
    "pendingPercent": 0,
    "other": 0,
    "hasOther": false,
    "skipped": 0,
    "hasSkipped": false
  },
  "results": [
    {
      "uuid": "cf322bc1-62b1-45d3-b853-85b18d5b139f",
      "title": "",
      "fullFile": "cypress\\integration\\taskGenerateTableDom.spec.js",
      "file": "cypress\\integration\\taskGenerateTableDom.spec.js",
      "beforeHooks": [],
      "afterHooks": [],
      "tests": [],
      "suites": [
        {
          "uuid": "5c0c5ad1-3d04-4f2c-b0ac-54c26eab8009",
          "title": "Generate table app",
          "fullFile": "",
          "file": "",
          "beforeHooks": [],
          "afterHooks": [],
          "tests": [
            {
              "title": "should create a table based on people.json file",
              "fullTitle": "Generate table app should create a table based on people.json file",
              "timedOut": null,
              "duration": 898,
              "state": "passed",
              "speed": "slow",
              "pass": true,
              "fail": false,
              "pending": false,
              "context": null,
              "code": "for (var i = 0; i < people.length; i++) {\n  cy.contains('tr', people[i].name).contains('td', people[i].born);\n  cy.contains('tr', people[i].name).contains('td', people[i].died);\n  cy.contains('tr', people[i].name).contains(('td', people[i].died) - ('td', people[i].born));\n  cy.contains('tr', people[i].name).contains('td', Math.ceil(people[i].died / 100));\n  cy.contains('tr', people[i].name).contains('td', people[i].sex === 'm' ? 'Male' : 'Female');\n}",
              "err": {},
              "uuid": "e5a47eaf-0248-44e4-99e5-6002d4ecd021",
              "parentUUID": "5c0c5ad1-3d04-4f2c-b0ac-54c26eab8009",
              "isHook": false,
              "skipped": false
            },
            {
              "title": "shouldn't contain fatherName, motherName and slug in table",
              "fullTitle": "Generate table app shouldn't contain fatherName, motherName and slug in table",
              "timedOut": null,
              "duration": 67,
              "state": "passed",
              "speed": "medium",
              "pass": true,
              "fail": false,
              "pending": false,
              "context": null,
              "code": "cy.get('tbody').contains('Petrus de Milliano').should('not.exist');\ncy.get('tbody').contains('Laurentia van Vlaenderen').should('not.exist');\ncy.get('tbody').contains('jan-van-brussel-1714').should('not.exist');",
              "err": {},
              "uuid": "bb846d8e-c05f-485a-ba58-82cf41d16825",
              "parentUUID": "5c0c5ad1-3d04-4f2c-b0ac-54c26eab8009",
              "isHook": false,
              "skipped": false
            }
          ],
          "suites": [],
          "passes": [
            "e5a47eaf-0248-44e4-99e5-6002d4ecd021",
            "bb846d8e-c05f-485a-ba58-82cf41d16825"
          ],
          "failures": [],
          "pending": [],
          "skipped": [],
          "duration": 965,
          "root": false,
          "rootEmpty": false,
          "_timeout": 2000
        }
      ],
      "passes": [],
      "failures": [],
      "pending": [],
      "skipped": [],
      "duration": 0,
      "root": true,
      "rootEmpty": true,
      "_timeout": 2000
    }
  ],
  "meta": {
    "mocha": {
      "version": "7.0.1"
    },
    "mochawesome": {
      "options": {
        "quiet": false,
        "reportFilename": "mochawesome",
        "saveHtml": false,
        "saveJson": true,
        "consoleReporter": "spec",
        "useInlineDiffs": false,
        "code": true
      },
      "version": "6.2.1"
    },
    "marge": {
      "options": {
        "reportDir": "raw_reports",
        "overwrite": false,
        "html": false,
        "json": true
      },
      "version": "5.1.0"
    }
  }
}